textcleaner2305/__init__.py
textcleaner2305/textcleaner2305.py
textcleaner2305-1.0.0.dist-info/LICENSE.txt
textcleaner2305-1.0.0.dist-info/METADATA
textcleaner2305-1.0.0.dist-info/WHEEL
textcleaner2305-1.0.0.dist-info/top_level.txt
textcleaner2305-1.0.0.dist-info/RECORD
